{
  "shuttlecock_i_weekend": [
    { "time": "08:15", "type": "R" },
    { "time": "08:20", "type": "R" },
    { "time": "08:30", "type": "R" },
    { "time": "08:40", "type": "R" },
    { "time": "08:50", "type": "R" },
    { "time": "09:00", "type": "R" },
    { "time": "09:15", "type": "R" },
    { "time": "09:20", "type": "R" },
    { "time": "09:30", "type": "R" },
    { "time": "09:40", "type": "R" },
    { "time": "09:50", "type": "R" },
    { "time": "10:00", "type": "R" },
    { "time": "10:15", "type": "R" },
    { "time": "10:20", "type": "R" },
    { "time": "10:30", "type": "R" },
    { "time": "10:40", "type": "R" },
    { "time": "10:50", "type": "R" },
    { "time": "11:00", "type": "R" },
    { "time": "11:15", "type": "R" },
    { "time": "11:20", "type": "R" },
    { "time": "11:30", "type": "R" },
    { "time": "11:40", "type": "R" },
    { "time": "11:50", "type": "R" },
    { "time": "12:00", "type": "R" },
    { "time": "12:15", "type": "R" },
    { "time": "12:20", "type": "R" },
    { "time": "12:30", "type": "R" },
    { "time": "12:40", "type": "R" },
    { "time": "12:50", "type": "R" },
    { "time": "13:00", "type": "R" },
    { "time": "13:15", "type": "R" },
    { "time": "13:20", "type": "R" },
    { "time": "13:30", "type": "R" },
    { "time": "13:40", "type": "R" },
    { "time": "13:50", "type": "R" },
    { "time": "14:00", "type": "R" },
    { "time": "14:15", "type": "R" },
    { "time": "14:20", "type": "R" },
    { "time": "14:30", "type": "R" },
    { "time": "14:40", "type": "R" },
    { "time": "14:50", "type": "R" },
    { "time": "15:00", "type": "R" },
    { "time": "15:15", "type": "R" },
    { "time": "15:20", "type": "R" },
    { "time": "15:30", "type": "R" },
    { "time": "15:40", "type": "R" },
    { "time": "15:50", "type": "R" },
    { "time": "16:00", "type": "R" },
    { "time": "16:15", "type": "R" },
    { "time": "17:15", "type": "R" },
    { "time": "18:15", "type": "R" },
    { "time": "19:15", "type": "R" },
    { "time": "20:15", "type": "R" },
    { "time": "21:15", "type": "R" }
  ]
}